twitter.common.git-0.3.11-py2.7-nspkg.pth
twitter/common/git/__init__.py
twitter.common.git-0.3.11.dist-info/DESCRIPTION.rst
twitter.common.git-0.3.11.dist-info/METADATA
twitter.common.git-0.3.11.dist-info/RECORD
twitter.common.git-0.3.11.dist-info/WHEEL
twitter.common.git-0.3.11.dist-info/metadata.json
twitter.common.git-0.3.11.dist-info/namespace_packages.txt
twitter.common.git-0.3.11.dist-info/top_level.txt
twitter.common.git-0.3.11.dist-info/zip-safe
